vyxal/Canvas.py
vyxal/LazyList.py
vyxal/__init__.py
vyxal/__main__.py
vyxal/context.py
vyxal/dictionary.py
vyxal/elements.py
vyxal/encoding.py
vyxal/helpers.py
vyxal/lexer.py
vyxal/main.py
vyxal/parse.py
vyxal/structure.py
vyxal/transpile.py
vyxal/vyncode.jar
vyxal-2.22.4.3.dist-info/LICENSE
vyxal-2.22.4.3.dist-info/METADATA
vyxal-2.22.4.3.dist-info/WHEEL
vyxal-2.22.4.3.dist-info/entry_points.txt
vyxal-2.22.4.3.dist-info/RECORD
