Metadata-Version: 2.1
Name: vyxal
Version: 2.22.4.3
Summary: A golfing language that has aspects of traditional programming languages.
Home-page: https://vyxal.pythonanywhere.com/
License: MIT
Requires-Python: >=3.9,<3.11
Classifier: License :: OSI Approved :: MIT License
Classifier: Programming Language :: Python :: 3
Classifier: Programming Language :: Python :: 3.9
Classifier: Programming Language :: Python :: 3.10
Requires-Dist: beautifulsoup4 (==4.12.2)
Requires-Dist: num2words (>=0.5.10,<0.6.0)
Requires-Dist: numpy (>=1.24.1,<2.0.0)
Requires-Dist: sympy (>=1.9,<2.0)
Project-URL: Repository, https://github.com/Vyxal/Vyxal/
